{
  "protagonist": {
    "width": 50,
    "weapons": {
      "low_level": [{
        "angle": 100,
        "preallocation": 15,
        "key": "sprites",
        "frame": "gun01",
        "width": 40,
        "relativePos": {
          "x": 0,
          "y": 0
        }
      }]
    }
  },
  "diagonal": {
    "frame": "enemyBlack1",
    "health": 100,
    "width": 50,
    "gold": 50,
    "velocity": {
      "min": {
        "x": 100,
        "y": 200
      },
      "max": {
        "x": 150,
        "y": 200
      }
    },
    "weapons": {
      "low_level": [{
        "angle": 90,
        "xPercentOffset": 0,
        "fireRate": 1000,
        "preallocation": 8,
        "key": "sprites",
        "frame": "gun01",
        "width": 40,
        "relativePos": {
          "x": 0,
          "y": 0
        }
      }]
    }
  }
}
